speedystar/__init__.py
speedystar/dynamics.py
speedystar/eject.py
speedystar/myexample.py
speedystar/observation.py
speedystar/saveload.py
speedystar/subsample.py
speedystar/utils/BaSeL_library.txt
speedystar/utils/MIST_bologrid_VISTABessellGaiaDECamLSST_-0.25_reduced.txt
speedystar/utils/MIST_bologrid_VISTABessellGaiaDECamLSST_0.0_reduced.txt
speedystar/utils/MIST_bologrid_VISTABessellGaiaDECamLSST_0.25_reduced.txt
speedystar/utils/MIST_photometry.py
speedystar/utils/McMillan17.py
speedystar/utils/MovingObjectPotential2.py
speedystar/utils/__init__.py
speedystar/utils/catstack.py
speedystar/utils/converttoplane.py
speedystar/utils/dustmap.py
speedystar/utils/gaia.py
speedystar/utils/hurley_stellar_evolution.py
speedystar/utils/interp_data_0.0.txt
speedystar/utils/mainsequence.py
speedystar/utils/mainsequence2.py
speedystar/utils/multifits.py
speedystar/utils/mwpotential.py
speedystar/utils/softeningtest.py
speedystar/utils/spectrum_data_-0.5.txt
speedystar/utils/spectrum_data_0.0.txt
speedystar/utils/spectrum_data_0.5.txt
speedystar/utils/test.txt
speedystar/utils/imfmaster/imf/__init__.py
speedystar/utils/imfmaster/imf/cmf.py
speedystar/utils/imfmaster/imf/distributions.py
speedystar/utils/imfmaster/imf/imf.py
speedystar/utils/imfmaster/imf/plf.py
speedystar/utils/imfmaster/imf/pmf.py
speedystar/utils/selectionfunctions/__init__.py
speedystar/utils/selectionfunctions/cog_ii.py
speedystar/utils/selectionfunctions/cog_v.py
speedystar/utils/selectionfunctions/config.py
speedystar/utils/selectionfunctions/equirectangular_map.py
speedystar/utils/selectionfunctions/fetch_utils.py
speedystar/utils/selectionfunctions/healpix_map.py
speedystar/utils/selectionfunctions/json_serializers.py
speedystar/utils/selectionfunctions/map.py
speedystar/utils/selectionfunctions/rrl_mateu_2020.py
speedystar/utils/selectionfunctions/sets.py
speedystar/utils/selectionfunctions/sfexceptions.py
speedystar/utils/selectionfunctions/source.py
speedystar/utils/selectionfunctions/std_paths.py
speedystar-1.0.1.dist-info/LICENSE.txt
speedystar-1.0.1.dist-info/METADATA
speedystar-1.0.1.dist-info/WHEEL
speedystar-1.0.1.dist-info/top_level.txt
speedystar-1.0.1.dist-info/RECORD
